clodputer/__init__.py
clodputer/cleanup.py
clodputer/cli.py
clodputer/config.py
clodputer/cron.py
clodputer/dashboard.py
clodputer/diagnostics.py
clodputer/environment.py
clodputer/executor.py
clodputer/logger.py
clodputer/menubar.py
clodputer/metrics.py
clodputer/onboarding.py
clodputer/queue.py
clodputer/settings.py
clodputer/watcher.py
clodputer/templates/__init__.py
clodputer/templates/calendar-sync.yaml
clodputer/templates/daily-email.yaml
clodputer/templates/file-watcher.yaml
clodputer/templates/manual-task.yaml
clodputer/templates/todo-triage.yaml
clodputer-0.1.0.dist-info/licenses/LICENSE
clodputer-0.1.0.dist-info/METADATA
clodputer-0.1.0.dist-info/WHEEL
clodputer-0.1.0.dist-info/entry_points.txt
clodputer-0.1.0.dist-info/top_level.txt
clodputer-0.1.0.dist-info/RECORD
