Metadata-Version: 2.4
Name: clodputer
Version: 0.1.0
Summary: Autonomous Claude Code automation system
Author-email: Rémy Olson <olson.remy@gmail.com>
License-Expression: MIT
Project-URL: Homepage, https://github.com/remyolson/clodputer
Project-URL: Documentation, https://github.com/remyolson/clodputer/tree/main/docs/planning
Project-URL: Repository, https://github.com/remyolson/clodputer
Project-URL: Issues, https://github.com/remyolson/clodputer/issues
Keywords: claude,automation,ai,assistant,cron
Classifier: Development Status :: 2 - Pre-Alpha
Classifier: Intended Audience :: Developers
Classifier: Programming Language :: Python :: 3
Classifier: Programming Language :: Python :: 3.9
Classifier: Programming Language :: Python :: 3.10
Classifier: Programming Language :: Python :: 3.11
Classifier: Programming Language :: Python :: 3.12
Classifier: Operating System :: MacOS
Requires-Python: >=3.9
License-File: LICENSE
Requires-Dist: click<9.0.0,>=8.0.0
Requires-Dist: pyyaml<7.0.0,>=6.0.0
Requires-Dist: psutil<7.0.0,>=6.0.0
Requires-Dist: watchdog<5.0.0,>=4.0.0
Requires-Dist: pydantic<3.0.0,>=2.0.0
Requires-Dist: rumps<0.5.0,>=0.4.0; sys_platform == "darwin"
Requires-Dist: croniter<3.0.0,>=2.0.0
Provides-Extra: dev
Requires-Dist: pytest>=7.0.0; extra == "dev"
Requires-Dist: pytest-mock>=3.0.0; extra == "dev"
Requires-Dist: pytest-cov>=4.1.0; extra == "dev"
Requires-Dist: black>=23.0.0; extra == "dev"
Requires-Dist: ruff>=0.1.0; extra == "dev"
Requires-Dist: mypy>=1.0.0; extra == "dev"
Dynamic: license-file
